{
  "dateFrom" : "2017-10-07T08:00:00+0200",
  "dateTo" : "2017-10-08T16:00:00+0200",
  "name" : "Macoun",
  "participants" : [
    {
      "company" : "ser.soft GmbH",
      "id" : 1,
      "isSpeaker" : true,
      "name" : "Daniel Friedrich"
    },
    {
      "company" : "ser.soft GmbH",
      "id" : 2,
      "isSpeaker" : true,
      "name" : "Florian Friedrich"
    },
    {
      "company" : null,
      "id" : 3,
      "isSpeaker" : false,
      "name" : "Hans Muster"
    },
    {
      "company" : "My Big Company AG",
      "id" : 4,
      "isSpeaker" : false,
      "name" : "Peter Beispiel"
    }
  ]
}
